model/__init__.py
model/base.py
model/keras/__init__.py
model/keras/yolo.py
model/keras/yolo3/__init__.py
model/keras/yolo3/model.py
model/keras/yolo3/utils.py
performance/__init__.py
performance/performance.py
performance/test_temp.py
cctv_analysis-0.0.2.dist-info/METADATA
cctv_analysis-0.0.2.dist-info/WHEEL
cctv_analysis-0.0.2.dist-info/top_level.txt
cctv_analysis-0.0.2.dist-info/RECORD
