Metadata-Version: 2.1
Name: cctv-analysis
Version: 0.0.2
Summary: A ready-to-use server to analyse cctv feeds. Pip install, boot up server, and make requests to analyse videos.
Home-page: https://github.com/midusi/cctv_analysis
Author: Juan Tomás Barrón - Gustavo Risso - Facundo Quiroga
Author-email: fquiroga@lidi.info.unlp.edu.ar
License: GNU Affero General Public License v3 or later (AGPLv3+)
Project-URL: Bug Tracker, https://github.com/midusi/cctv_analysis/issues
Project-URL: Documentation, https://github.com/midusi/cctv_analysis
Project-URL: Source Code, https://github.com/midusi/cctv_analysis
Platform: UNKNOWN
Classifier: Programming Language :: Python
Classifier: Programming Language :: Python :: 3
Classifier: Programming Language :: Python :: 3.6
Classifier: Programming Language :: Python :: Implementation :: CPython
Classifier: License :: OSI Approved :: Python Software Foundation License
Classifier: License :: OSI Approved :: GNU Affero General Public License v3 or later (AGPLv3+)
Requires-Python: >=3.6.0
Requires-Dist: flask
Requires-Dist: gdown
Requires-Dist: numpy
Requires-Dist: opencv-python
Requires-Dist: tensorflow-gpu
Requires-Dist: keras
Requires-Dist: pillow
Requires-Dist: matplotlib
Requires-Dist: tqdm
